supbot/__init__.py
supbot/__main__.py
supbot/action.py
supbot/api.py
supbot/app_driver.py
supbot/exceptions.py
supbot/g.py
supbot/helper.py
supbot/looper.py
supbot/results.py
supbot/service_manager.py
supbot/system.py
supbot/statemanager/__init__.py
supbot/statemanager/state.py
supbot/statemanager/transition.py
supbot-0.2.9.dist-info/LICENSE
supbot-0.2.9.dist-info/METADATA
supbot-0.2.9.dist-info/WHEEL
supbot-0.2.9.dist-info/entry_points.txt
supbot-0.2.9.dist-info/top_level.txt
supbot-0.2.9.dist-info/RECORD
