Metadata-Version: 2.1
Name: supbot
Version: 0.2.9
Summary: An unofficial WhatsApp automation library
Home-page: https://github.com/adsau59/supbot2
Author: Adam Saudagar
Author-email: adam_saudagar@live.com
License: MIT
Project-URL: Bug Reports, https://github.com/adsau59/supbot2/issues
Project-URL: Funding, https://www.paypal.me/AdamSaudagar
Project-URL: Say Thanks!, http://discord.definex.in
Project-URL: Source, https://github.com/adsau59/supbot2/
Keywords: yosup whaatsapp-api supbot supbot2
Platform: UNKNOWN
Classifier: Development Status :: 3 - Alpha
Classifier: Intended Audience :: Developers
Classifier: License :: OSI Approved :: MIT License
Classifier: Programming Language :: Python :: 3.7
Classifier: Programming Language :: Python :: 3.8
Requires-Python: >=3.7
Requires-Dist: docopt
Requires-Dist: selenium
Requires-Dist: typeguard
Requires-Dist: Appium-Python-Client
Requires-Dist: prompt-toolkit
